bomapi/__init__.py
bomapi/aio.py
bomapi/data_structures.py
bomapi/exceptions.py
bomapi-0.1.0.dist-info/LICENSE
bomapi-0.1.0.dist-info/WHEEL
bomapi-0.1.0.dist-info/METADATA
bomapi-0.1.0.dist-info/RECORD
