Metadata-Version: 2.1
Name: bomapi
Version: 0.1.0
Summary: Python interface to the Australia Government BOM Weather API
Home-page: https://github.com/timsavage/bomapi
License: BSD-3-Clause
Author: Tim Savage
Author-email: tim@savage.company
Requires-Python: >=3.8,<4.0
Classifier: License :: OSI Approved :: BSD License
Classifier: Programming Language :: Python :: 3
Classifier: Programming Language :: Python :: 3.10
Classifier: Programming Language :: Python :: 3.8
Classifier: Programming Language :: Python :: 3.9
Requires-Dist: httpx (>=0.22.0,<0.23.0)
Project-URL: Bug Tracker, https://github.com/timsavage/bomapi/issues
Project-URL: Repository, https://github.com/timsavage/bomapi
